tritonparse/__init__.py
tritonparse/__main__.py
tritonparse/cli.py
tritonparse/common.py
tritonparse/context_manager.py
tritonparse/event_diff.py
tritonparse/extract_source_mappings.py
tritonparse/ir_analysis.py
tritonparse/ir_parser.py
tritonparse/mapper.py
tritonparse/shared_vars.py
tritonparse/source_type.py
tritonparse/sourcemap_utils.py
tritonparse/structured_logging.py
tritonparse/tp_logger.py
tritonparse/trace_processor.py
tritonparse/utils.py
tritonparse/reproducer/__init__.py
tritonparse/reproducer/cli.py
tritonparse/reproducer/function_extractor.py
tritonparse/reproducer/orchestrator.py
tritonparse/reproducer/placeholder_replacer.py
tritonparse/reproducer/types.py
tritonparse/reproducer/utils.py
tritonparse/reproducer/ingestion/ndjson.py
tritonparse/reproducer/templates/__init__.py
tritonparse/reproducer/templates/example.py
tritonparse/reproducer/templates/loader.py
tritonparse/reproducer/templates/tritonbench.py
tritonparse/tools/__init__.py
tritonparse/tools/decompress_bin_ndjson.py
tritonparse/tools/disasm.py
tritonparse/tools/format_fix.py
tritonparse/tools/load_tensor.py
tritonparse/tools/prettify_ndjson.py
tritonparse/tools/readme.md
tritonparse-0.3.1.dist-info/licenses/LICENSE
tritonparse-0.3.1.dist-info/METADATA
tritonparse-0.3.1.dist-info/WHEEL
tritonparse-0.3.1.dist-info/entry_points.txt
tritonparse-0.3.1.dist-info/top_level.txt
tritonparse-0.3.1.dist-info/RECORD
