Metadata-Version: 2.4
Name: tritonparse
Version: 0.3.1
Summary: TritonParse: A Compiler Tracer, Visualizer, and mini-Reproducer Generator for Triton Kernels
Author-email: Yueming Hao <yhao@meta.com>
License-Expression: BSD-3-Clause
Project-URL: Homepage, https://github.com/meta-pytorch/tritonparse
Requires-Python: >=3.10
License-File: LICENSE
Provides-Extra: triton
Requires-Dist: triton>3.3.1; extra == "triton"
Provides-Extra: pytorch-triton
Requires-Dist: pytorch-triton>=3.4.0; extra == "pytorch-triton"
Provides-Extra: test
Requires-Dist: coverage>=7.0.0; extra == "test"
Dynamic: license-file
